contiguity_base/__init__.py
contiguity_base/base.py
contiguity_base/py.typed
contiguity_base-1.1.1.dist-info/LICENSE.txt
contiguity_base-1.1.1.dist-info/METADATA
contiguity_base-1.1.1.dist-info/WHEEL
contiguity_base-1.1.1.dist-info/top_level.txt
contiguity_base-1.1.1.dist-info/RECORD
