Metadata-Version: 2.1
Name: contiguity_base
Version: 1.1.1
Summary: The official Python SDK for Contiguity Base
Author-email: Contiguity <help@contiguity.support>
License: MIT License
Project-URL: Repository, https://github.com/contiguity/base-python
Keywords: python,contiguity,deta,base,database
Classifier: Development Status :: 3 - Alpha
Classifier: Intended Audience :: Developers
Classifier: License :: OSI Approved :: MIT License
Classifier: Operating System :: OS Independent
Classifier: Programming Language :: Python :: 3
Classifier: Topic :: Utilities
Classifier: Typing :: Typed
Requires-Python: >=3.9
License-File: LICENSE.txt
Requires-Dist: requests <3.0.0,>=2.25.1
